hoocron_plugin/websocket/__init__.py
hoocron_plugin_websocket-0.0.1.dist-info/LICENSE
hoocron_plugin_websocket-0.0.1.dist-info/METADATA
hoocron_plugin_websocket-0.0.1.dist-info/WHEEL
hoocron_plugin_websocket-0.0.1.dist-info/top_level.txt
hoocron_plugin_websocket-0.0.1.dist-info/RECORD
