Metadata-Version: 2.1
Name: hoocron-plugin-websocket
Version: 0.0.1
Summary: Websocket plugin for Hoocron
Home-page: https://github.com/yaroslaff/hoocron-plugin-websocket
Author: Yaroslav Polyakov
Author-email: yaroslaff@gmail.com
License: MIT
Platform: UNKNOWN
Classifier: Development Status :: 3 - Alpha
Classifier: Intended Audience :: Developers
Classifier: License :: OSI Approved :: MIT License
Classifier: Programming Language :: Python :: 3.4
Requires-Python: >=3
Requires-Dist: hoocron
Requires-Dist: python-socketio[client]
Requires-Dist: websocket-client
